pyfaidx/__init__.py
pyfaidx/cli.py
pyfaidx-0.9.0.2.dist-info/licenses/LICENSE
pyfaidx-0.9.0.2.dist-info/METADATA
pyfaidx-0.9.0.2.dist-info/WHEEL
pyfaidx-0.9.0.2.dist-info/entry_points.txt
pyfaidx-0.9.0.2.dist-info/top_level.txt
pyfaidx-0.9.0.2.dist-info/RECORD
