Metadata-Version: 2.4
Name: pyfaidx
Version: 0.9.0.2
Summary: pyfaidx: efficient pythonic random access to fasta subsequences
Author-email: Matthew Shirley <mdshw5@gmail.com>
License: BSD-3-Clause
Project-URL: Homepage, https://github.com/mdshw5/pyfaidx/
Project-URL: Author homepage, http://mattshirley.com
Classifier: Development Status :: 5 - Production/Stable
Classifier: License :: OSI Approved :: BSD License
Classifier: Environment :: Console
Classifier: Intended Audience :: Science/Research
Classifier: Natural Language :: English
Classifier: Operating System :: Unix
Classifier: Programming Language :: Python :: 3.11
Classifier: Programming Language :: Python :: 3.10
Classifier: Programming Language :: Python :: 3.9
Classifier: Programming Language :: Python :: 3.8
Classifier: Programming Language :: Python :: 3.7
Classifier: Programming Language :: Python :: Implementation :: PyPy
Classifier: Topic :: Scientific/Engineering :: Bio-Informatics
Requires-Python: >=3.7
License-File: LICENSE
Requires-Dist: importlib_metadata; python_version < "3.8"
Requires-Dist: packaging
Dynamic: license-file
